{
  "name": "Garrett Norton",
  "age": 54,
  "address": {
    "street": "Bupac Point",
    "city": "Fobalef",
    "state": "TX",
    "zip": "23509"
  },
  "contact": {
    "phone": "(547) 609-4961",
    "servicePhone": "800778363"
  },
  "birthday": "1972-07-04T04:29:47.674Z",
  "ip": "62.221.175.247",
  "foo": "bar",
  "profile": {
    "about": "Vemep cij vuljetu judbigkul rojfura fuvlu ro ji le gap veajiode for gej ep taisojov cogadune odnuskaw. Tavip tupogwa rifudloh havdovnav isfitik jemves moziced afo fecu muw ajbuca tu jido duw go wug ka. Luzaz woul dagolsi zipi sohkidga unihekmez sofabu vikboira wejosmu alpohov wo neneawe fanoru. Wauk apeti sarbo kon zuumodi jaawiup bouwof lizipir hebhegtih dabfe ca ci pipoc bocfe ej wanu matwi zidej. Badukpa ne fobit homdahin rebker darfij agado gedozce kanrusbiv ba ihotum vivtekel wapotjan kipfez huhta eruzivwal ba. Raup havlu gicis manzohev pas odoopcet savu oto ogukwa mebdogon uleibe soufe umeor.",
    "bio": "Unoatzud kip ilza enu hihjakbo detow bernofe vin ovgab wutle turil cizutal so tevoug rufruzfuv kih tate. Ipoke wa kiipawam joc ekara bese ibaedpo kema cotka rap evowozif kos vaminci fusdov pe agujikdog. Iz jado irozew wus re ohajor mocipu oz evoov bigbi gaz eksius so zujatufis ahiricec daze cupehu kirgore. Ilu cetju tugiz tur ap gakeme ceska dom zehnipniv naipu mishukun rawgodolu ut elo. Topjajgo mir fajir vot nadom hunocvi hi mihegova epufem huh noguvkan vu do hekav ka."
  },
  "apiKey": "21608fc1ede27c6db46b6ab9cd1ebf9d2fbc654f1b0394f0acc72dc98001fb53",
  "currency": {
    "code": "BND",
    "name": "Brunei Darussalam Dollar"
  }
}